ipychat/__init__.py
ipychat/__version__.py
ipychat/cli.py
ipychat/config.py
ipychat/context.py
ipychat/magic.py
ipychat/models.py
ipychat/ui.py
ipychat/providers/__init__.py
ipychat/providers/anthropic.py
ipychat/providers/base.py
ipychat/providers/google.py
ipychat/providers/openai.py
ipychat-0.2.1.dist-info/LICENSE
ipychat-0.2.1.dist-info/METADATA
ipychat-0.2.1.dist-info/WHEEL
ipychat-0.2.1.dist-info/entry_points.txt
ipychat-0.2.1.dist-info/top_level.txt
ipychat-0.2.1.dist-info/RECORD
