Metadata-Version: 2.1
Name: ipychat
Version: 0.2.1
Summary: The AI IPython
Author-email: Vinayak Mehta <vmehta94@gmail.com>
License: Apache-2.0
Project-URL: Homepage, https://github.com/vinayak-mehta/ipychat
Project-URL: Changelog, https://github.com/vinayak-mehta/ipychat/releases
Project-URL: Issues, https://github.com/vinayak-mehta/ipychat/issues
Project-URL: CI, https://github.com/vinayak-mehta/ipychat/actions
Classifier: License :: OSI Approved :: Apache Software License
Classifier: Programming Language :: Python :: 3.11
Classifier: Programming Language :: Python :: 3.12
Classifier: Programming Language :: Python :: 3.13
Requires-Python: >=3.9
License-File: LICENSE
Requires-Dist: click
Requires-Dist: rich>=10.0.0
Requires-Dist: questionary>=2.0.1
Requires-Dist: ipython<8.18.0
Requires-Dist: toml>=0.10.0
Requires-Dist: openai>=1.0.0
Requires-Dist: anthropic>=0.5.0
Requires-Dist: google-generativeai>=0.8.3
Provides-Extra: dev
Requires-Dist: ruff; extra == "dev"
Requires-Dist: pytest; extra == "dev"
Requires-Dist: pytest-cov; extra == "dev"
Requires-Dist: twine; extra == "dev"
Requires-Dist: build; extra == "dev"
Provides-Extra: test
Requires-Dist: pandas; extra == "test"
Requires-Dist: numpy; extra == "test"
